[
  {
    "id": "pmc10131759",
    "paper_id": "pmc10131759",
    "title": "Mobile Device Use While Crossing the Street: Utilizing the Theory of Planned Behavior",
    "year": 2019,
    "venue": "Transportation Research Part F",
    "paper_type": "research_article",
    "domain_role": "prose_reference",
    "access": "oa_fulltext",
    "source_url": "https://www.ncbi.nlm.nih.gov/pmc/articles/PMC10131759/",
    "status": "extracted",
    "notes": "Strong intro and discussion prose; evidence-grounded structure."
  },
  {
    "id": "doi:10.1016/j.trf.2015.11.003",
    "paper_id": "doi:10.1016/j.trf.2015.11.003",
    "title": "Introducing human factors in pedestrian crossing behaviour models",
    "year": 2016,
    "venue": "Transportation Research Part F",
    "paper_type": "review",
    "domain_role": "structure_reference",
    "access": "abstract_only",
    "source_url": "https://doi.org/10.1016/j.trf.2015.11.003",
    "status": "queued",
    "notes": "Review paper; expected to show taxonomy and gap structure."
  },
  {
    "id": "doi:10.1177/0361198118759075",
    "paper_id": "doi:10.1177/0361198118759075",
    "title": "Modeling Pedestrian Crossing Behavior and Safety at Signalized Intersections",
    "year": 2018,
    "venue": "Transportation Research Record",
    "paper_type": "research_article",
    "domain_role": "structure_reference",
    "access": "abstract_only",
    "source_url": "https://doi.org/10.1177/0361198118759075",
    "status": "queued",
    "notes": "Signalized intersection focus; methodological diversity."
  },
  {
    "id": "doi:10.1016/j.aap.2018.02.016",
    "paper_id": "doi:10.1016/j.aap.2018.02.016",
    "title": "Mobile phone use while crossing the street: A systematic review",
    "year": 2018,
    "venue": "Accident Analysis & Prevention",
    "paper_type": "review",
    "domain_role": "both",
    "access": "abstract_only",
    "source_url": "https://doi.org/10.1016/j.aap.2018.02.016",
    "status": "queued",
    "notes": "Systematic review of distraction; strong gap and methodology structure."
  },
  {
    "id": "doi:10.1016/j.trc.2022.104666",
    "paper_id": "doi:10.1016/j.trc.2022.104666",
    "title": "Pedestrian behavior in shared spaces with autonomous vehicles: A review",
    "year": 2022,
    "venue": "Transportation Research Part C",
    "paper_type": "review",
    "domain_role": "both",
    "access": "abstract_only",
    "source_url": "https://doi.org/10.1016/j.trc.2022.104666",
    "status": "queued",
    "notes": "AV-pedestrian interaction review; recent gap and methodology framing."
  },
  {
    "id": "doi:10.1016/j.trf.2021.07.003",
    "paper_id": "doi:10.1016/j.trf.2021.07.003",
    "title": "Factors influencing pedestrian decision-making at traffic lights: A review",
    "year": 2021,
    "venue": "Transportation Research Part F",
    "paper_type": "review",
    "domain_role": "structure_reference",
    "access": "abstract_only",
    "source_url": "https://doi.org/10.1016/j.trf.2021.07.003",
    "status": "queued",
    "notes": "Determinants/factors review; strong factor taxonomy structure."
  },
  {
    "id": "doi:10.1109/TITS.2019.2935807",
    "paper_id": "doi:10.1109/TITS.2019.2935807",
    "title": "Pedestrian Models for Autonomous Driving Part II: High-Level Behavior Models",
    "year": 2020,
    "venue": "IEEE Transactions on Intelligent Transportation Systems",
    "paper_type": "review",
    "domain_role": "both",
    "access": "abstract_only",
    "source_url": "https://doi.org/10.1109/TITS.2019.2935807",
    "status": "queued",
    "notes": "Two-part review; Part II covers high-level behavior modeling; good methodology taxonomy."
  },
  {
    "id": "pmc8912959",
    "paper_id": "pmc8912959",
    "title": "Factors Influencing Pedestrian Behavior at Signalized Crosswalks: A Review",
    "year": 2022,
    "venue": "Sustainability (OA)",
    "paper_type": "review",
    "domain_role": "both",
    "access": "oa_fulltext",
    "source_url": "https://www.ncbi.nlm.nih.gov/pmc/articles/PMC8912959/",
    "status": "queued",
    "notes": "Recent OA review; factor taxonomy + methodological comparison structure."
  }
]
